{
  "title": "اخدمني",
  "titleTemplate": "تنظيف منازل | مكافحة حشرات | نقل عفش | العامل الماهر",
  "welcomeText": "# خدمات التنظيف المنزلية,خدمات نقل وتخزين الأثاث,خدمات مكافحة الحشرات,خدمات الصيانة المنزلية.\n\nيمكنكم الاطلاع على جميع خدماتنا بالخلال الضغط على المدينة المراد المعرفة عن الخدمات المقدمة بها بالكامل و لمعرفة المزيد من التفاصيل علما بان شركة اخدمنى تقدم جميع الخدمات التى تقدم بالمنزل فى المملكة العربية السعودية مثل :\n\n[سباك بالمنزل](https://e5dmny.com/service/plumbing-foundation-works) - [غسيل مكيفات](https://e5dmny.com/service/air-conditioner-washing-and-cleaning) - [صيانة مكيفات و تعبئة فريون](https://e5dmny.com/service/air-conditioner-installation-and-maintenance) - [كهربائي منازل](https://e5dmny.com/service/electrician-services) - [كشف تسربات المياه](https://e5dmny.com/service/water-leak-detection) - [تسليك مجارى](https://e5dmny.com/service/sewage-suction-sewage-wiring) - [عزل اسطح](https://e5dmny.com/service/roof-insulation) - عزل خزانات - ترميم منازل و معالجة شروخ الجدران و تعشيش الخرسانة - تنظيف مجالس - مكافحة حشرات - نقل اثاث - تنظيف سجاد - رش مبيدات - تخزين اثاث - تنظيف شقق - رش دفان - تنظيف فلل - رش الصراصير - تنظيف خزانات - رش البق - تنظيف فرشات ( موكيت - ستائر-شركة غسيل مراتب السرير ) - ابادة فئران - تنظيف الحوش - طارد حمام - تنظيف سيارات بالمنزل.",
  "logo": "/images/uploads/logo.png",
  "icon": "/images/uploads/logo.png",
  "loadingColor": "#0b3765",
  "seoDescription": "اخدمنى© للخدمات المنزلية | تنظيف | مكافحة حشرات | نقل عفش",
  "seoMetaImage": ""
}